cosmic_ray_celery3_engine/__init__.py
cosmic_ray_celery3_engine/app.py
cosmic_ray_celery3_engine/engine.py
cosmic_ray_celery3_engine/version.py
cosmic_ray_celery3_engine/worker.py
cosmic_ray_celery3_engine-0.0.0.dist-info/DESCRIPTION.rst
cosmic_ray_celery3_engine-0.0.0.dist-info/METADATA
cosmic_ray_celery3_engine-0.0.0.dist-info/RECORD
cosmic_ray_celery3_engine-0.0.0.dist-info/WHEEL
cosmic_ray_celery3_engine-0.0.0.dist-info/entry_points.txt
cosmic_ray_celery3_engine-0.0.0.dist-info/metadata.json
cosmic_ray_celery3_engine-0.0.0.dist-info/top_level.txt
